membrowse/__init__.py
membrowse/cli.py
membrowse/py.typed
membrowse/analysis/__init__.py
membrowse/analysis/defaults.py
membrowse/analysis/dwarf.py
membrowse/analysis/mapper.py
membrowse/analysis/sections.py
membrowse/analysis/sources.py
membrowse/analysis/symbols.py
membrowse/api/__init__.py
membrowse/api/client.py
membrowse/auth/__init__.py
membrowse/auth/strategy.py
membrowse/commands/__init__.py
membrowse/commands/onboard.py
membrowse/commands/report.py
membrowse/core/__init__.py
membrowse/core/analyzer.py
membrowse/core/exceptions.py
membrowse/core/generator.py
membrowse/core/models.py
membrowse/linker/__init__.py
membrowse/linker/cli.py
membrowse/linker/elf_info.py
membrowse/linker/parser.py
membrowse/utils/__init__.py
membrowse/utils/budget_alerts.py
membrowse/utils/formatter.py
membrowse/utils/git.py
membrowse/utils/github.py
membrowse/utils/github_comment.py
membrowse/utils/github_common.py
membrowse/utils/url.py
membrowse-1.0.9.dist-info/licenses/LICENSE
membrowse-1.0.9.dist-info/METADATA
membrowse-1.0.9.dist-info/WHEEL
membrowse-1.0.9.dist-info/entry_points.txt
membrowse-1.0.9.dist-info/top_level.txt
membrowse-1.0.9.dist-info/RECORD
