Metadata-Version: 2.4
Name: membrowse
Version: 1.0.9
Summary: Memory footprint analysis tools for embedded firmware
Author-email: MemBrowse <support@membrowse.com>
Maintainer-email: MemBrowse <support@membrowse.com>
Project-URL: Homepage, https://membrowse.com
Project-URL: Documentation, https://github.com/membrowse/membrowse-action#readme
Project-URL: Repository, https://github.com/membrowse/membrowse-action
Project-URL: Issues, https://github.com/membrowse/membrowse-action/issues
Project-URL: Changelog, https://github.com/membrowse/membrowse-action/blob/main/CHANGELOG.md
Keywords: embedded,firmware,memory,analysis,elf,linker,dwarf,footprint,stm32,esp32,arm,risc-v
Classifier: Development Status :: 4 - Beta
Classifier: Intended Audience :: Developers
Classifier: Topic :: Software Development :: Build Tools
Classifier: Topic :: Software Development :: Embedded Systems
Classifier: Topic :: System :: Hardware
Classifier: Programming Language :: Python :: 3
Classifier: Programming Language :: Python :: 3.7
Classifier: Programming Language :: Python :: 3.8
Classifier: Programming Language :: Python :: 3.9
Classifier: Programming Language :: Python :: 3.10
Classifier: Programming Language :: Python :: 3.11
Classifier: Programming Language :: Python :: 3.12
Classifier: Operating System :: OS Independent
Classifier: Environment :: Console
Requires-Python: >=3.7
License-File: LICENSE
Requires-Dist: pyelftools>=0.29
Requires-Dist: requests>=2.25.0
Requires-Dist: cxxfilt>=0.3.0
Dynamic: license-file
